yet_another_imod_wrapper/__init__.py
yet_another_imod_wrapper/_cli.py
yet_another_imod_wrapper/constants.py
yet_another_imod_wrapper/fiducials.py
yet_another_imod_wrapper/patch_tracking.py
yet_another_imod_wrapper/batchruntomo_config/fiducials.adoc
yet_another_imod_wrapper/batchruntomo_config/patch_tracking.adoc
yet_another_imod_wrapper/utils/__init__.py
yet_another_imod_wrapper/utils/binning.py
yet_another_imod_wrapper/utils/etomo.py
yet_another_imod_wrapper/utils/installation.py
yet_another_imod_wrapper/utils/io.py
yet_another_imod_wrapper/utils/xf.py
yet_another_imod_wrapper-0.1.2.dist-info/METADATA
yet_another_imod_wrapper-0.1.2.dist-info/WHEEL
yet_another_imod_wrapper-0.1.2.dist-info/entry_points.txt
yet_another_imod_wrapper-0.1.2.dist-info/licenses/LICENSE
yet_another_imod_wrapper-0.1.2.dist-info/RECORD
